todo_utils/__init__.py
todo_utils/console_helper.py
todo_utils/constants.py
todo_utils/file_utils.py
todo_utils/manager.py
todo_utils/scan_codebase.py
todo_utils/system_caller.py
todo_utils/update_todo_md.py
todo_utils/util.py
todo_utils/conf/config.yaml
todo_utils-0.1.0.dist-info/AUTHORS.rst
todo_utils-0.1.0.dist-info/METADATA
todo_utils-0.1.0.dist-info/WHEEL
todo_utils-0.1.0.dist-info/entry_points.txt
todo_utils-0.1.0.dist-info/top_level.txt
todo_utils-0.1.0.dist-info/RECORD
