Metadata-Version: 2.1
Name: todo_utils
Version: 0.1.0
Summary: Convenient tool for scanning entire codebase to find TODO and FIXME comments and then updating the TODO.md.
Home-page: https://github.com/jai-python3/todo-utils
Author: Jaideep Sundaram
Author-email: jai.python3@gmail.com
Keywords: todo_utils
Classifier: Development Status :: 2 - Pre-Alpha
Classifier: Intended Audience :: Developers
Classifier: Natural Language :: English
Classifier: Programming Language :: Python :: 3
Classifier: Programming Language :: Python :: 3.6
Classifier: Programming Language :: Python :: 3.7
Classifier: Programming Language :: Python :: 3.8
Requires-Python: >=3.6
License-File: AUTHORS.rst
Requires-Dist: Click >=7.0
Requires-Dist: PyYAML
Requires-Dist: Rich
Requires-Dist: pydantic
